moat_ble/__init__.py
moat_ble/main.py
moat_ble/py.typed
moat_ble-0.0.1.dist-info/LICENSE
moat_ble-0.0.1.dist-info/WHEEL
moat_ble-0.0.1.dist-info/METADATA
moat_ble-0.0.1.dist-info/RECORD
